hypo/__init__.py
hypo/cfg.py
hypo/experiment.py
hypo/ext.py
hypo/hypo.py
hypo/metrics.py
hypo/nodes.py
hypo/resources.py
hypo_run-1.0.1.dist-info/licenses/LICENSE.txt
hypo_run-1.0.1.dist-info/METADATA
hypo_run-1.0.1.dist-info/WHEEL
hypo_run-1.0.1.dist-info/entry_points.txt
hypo_run-1.0.1.dist-info/top_level.txt
hypo_run-1.0.1.dist-info/RECORD
