Metadata-Version: 2.4
Name: hypo-run
Version: 1.0.1
Summary: A CLI tool to run the complex experiments
Author-email: ruimox <aruix@outlook.com>
Maintainer-email: ruimox <aruix@outlook.com>
License: Copyright (c) 2016 The Python Packaging Authority (PyPA)
Project-URL: Homepage, https://github.com/aruiplex/hypo
Project-URL: Bug Reports, https://github.com/aruiplex/hypo
Project-URL: Funding, https://github.com/aruiplex/hypo
Project-URL: Say Thanks!, https://github.com/aruiplex/hypo
Project-URL: Source, https://github.com/aruiplex/hypo
Keywords: cli tool,experiment,Parallel controller
Classifier: Intended Audience :: Developers
Classifier: Topic :: Software Development :: Build Tools
Classifier: License :: OSI Approved :: MIT License
Classifier: Programming Language :: Python :: 3
Classifier: Programming Language :: Python :: 3.8
Classifier: Programming Language :: Python :: 3.9
Classifier: Programming Language :: Python :: 3.10
Classifier: Programming Language :: Python :: 3.11
Classifier: Programming Language :: Python :: 3.12
Classifier: Programming Language :: Python :: 3 :: Only
Requires-Python: >=3.8
License-File: LICENSE.txt
Requires-Dist: loguru
Requires-Dist: GPUtil
Requires-Dist: alive_progress
Provides-Extra: dev
Requires-Dist: pandas; extra == "dev"
Requires-Dist: torchshow; extra == "dev"
Dynamic: license-file
